<annotation>
	<folder></folder>
	<filename>58fbee99-23d2-11e8-a6a3-ec086b02610b_jpg.rf.d8e0d7010c075ca40592377c5818ef99.jpg</filename>
	<path>58fbee99-23d2-11e8-a6a3-ec086b02610b_jpg.rf.d8e0d7010c075ca40592377c5818ef99.jpg</path>
	<source>
		<database>roboflow.com</database>
	</source>
	<size>
		<width>1024</width>
		<height>747</height>
		<depth>3</depth>
	</size>
	<segmented>0</segmented>
	<object>
		<name>rabbit</name>
		<pose>Unspecified</pose>
		<truncated>0</truncated>
		<difficult>0</difficult>
		<occluded>0</occluded>
		<bndbox>
			<xmin>180</xmin>
			<xmax>280</xmax>
			<ymin>527</ymin>
			<ymax>633</ymax>
		</bndbox>
	</object>
</annotation>
