<annotation>
	<folder></folder>
	<filename>5971f828-23d2-11e8-a6a3-ec086b02610b_jpg.rf.d69fd83d51e6fe882d7ffbd342659b47.jpg</filename>
	<path>5971f828-23d2-11e8-a6a3-ec086b02610b_jpg.rf.d69fd83d51e6fe882d7ffbd342659b47.jpg</path>
	<source>
		<database>roboflow.com</database>
	</source>
	<size>
		<width>1024</width>
		<height>747</height>
		<depth>3</depth>
	</size>
	<segmented>0</segmented>
	<object>
		<name>coyote</name>
		<pose>Unspecified</pose>
		<truncated>0</truncated>
		<difficult>0</difficult>
		<occluded>0</occluded>
		<bndbox>
			<xmin>13</xmin>
			<xmax>157</xmax>
			<ymin>379</ymin>
			<ymax>541</ymax>
		</bndbox>
	</object>
</annotation>
