<annotation>
	<folder></folder>
	<filename>59929047-23d2-11e8-a6a3-ec086b02610b_jpg.rf.490413e742c221d45883c0dfc00c4c9a.jpg</filename>
	<path>59929047-23d2-11e8-a6a3-ec086b02610b_jpg.rf.490413e742c221d45883c0dfc00c4c9a.jpg</path>
	<source>
		<database>roboflow.com</database>
	</source>
	<size>
		<width>1024</width>
		<height>747</height>
		<depth>3</depth>
	</size>
	<segmented>0</segmented>
	<object>
		<name>raccoon</name>
		<pose>Unspecified</pose>
		<truncated>0</truncated>
		<difficult>0</difficult>
		<occluded>0</occluded>
		<bndbox>
			<xmin>346</xmin>
			<xmax>568</xmax>
			<ymin>507</ymin>
			<ymax>730</ymax>
		</bndbox>
	</object>
</annotation>
